{
	"configurations" : 
	[
		{
			"directories" : 
			[
				{
					"build" : ".",
					"hasInstallRule" : true,
					"jsonFile" : "directory-.-c677e95a65ed7396c1d2.json",
					"minimumCMakeVersion" : 
					{
						"string" : "3.10.2"
					},
					"projectIndex" : 0,
					"source" : ".",
					"targetIndexes" : 
					[
						0,
						1
					]
				}
			],
			"name" : "",
			"projects" : 
			[
				{
					"directoryIndexes" : 
					[
						0
					],
					"name" : "wamv_navigation",
					"targetIndexes" : 
					[
						0,
						1
					]
				}
			],
			"targets" : 
			[
				{
					"directoryIndex" : 0,
					"id" : "uninstall::@6890427a1f51a3e7e1df",
					"jsonFile" : "target-uninstall-c6c4655a787c90b0cca1.json",
					"name" : "uninstall",
					"projectIndex" : 0
				},
				{
					"directoryIndex" : 0,
					"id" : "wamv_navigation_uninstall::@6890427a1f51a3e7e1df",
					"jsonFile" : "target-wamv_navigation_uninstall-df2329fb3ac371e7c1cc.json",
					"name" : "wamv_navigation_uninstall",
					"projectIndex" : 0
				}
			]
		}
	],
	"kind" : "codemodel",
	"paths" : 
	{
		"build" : "/home/luca002/proj_ws/build/wamv_navigation",
		"source" : "/home/luca002/proj_ws/src/wamv_navigation"
	},
	"version" : 
	{
		"major" : 2,
		"minor" : 6
	}
}
